igorpy-0.0.5.data/data/LICENSE
igorpy-0.0.5.data/data/README.md
pygor3/AIRR.py
pygor3/IgorBestScenarios.py
pygor3/IgorDefaults.py
pygor3/IgorDictionaries.py
pygor3/IgorIO.py
pygor3/IgorIndexedSequence.py
pygor3/IgorIndexedSequencesDB.py
pygor3/IgorSQL.py
pygor3/IgorSqliteDB.py
pygor3/IgorSqliteDBBestScenarios.py
pygor3/__init__.py
pygor3/imgt.py
pygor3/utils.py
pygor3/demo/data/IgL/IgL_seqs_memory_Functional.txt
pygor3/demo/data/IgL/IgL_seqs_memory_Nofunctional.txt
pygor3/demo/data/IgL/IgL_seqs_naive_Functional.txt
pygor3/demo/data/IgL/IgL_seqs_naive_Functional_small.txt
pygor3/demo/data/IgL/IgL_seqs_naive_Nofunctional.txt
pygor3/scripts/__init__.py
pygor3/scripts/all_gene_alignments_id.py
pygor3/scripts/bs_export.py
pygor3/scripts/bs_pairwise_prob.py
pygor3/scripts/cli.py
pygor3/scripts/download_imgt_gene_templates.py
pygor3/scripts/get_imgt_data.py
pygor3/scripts/infer_sequences.py
pygor3/scripts/load_database.py
pygor3/scripts/model_create.py
pygor3/scripts/model_export.py
pygor3/scripts/model_plot.py
pygor3/scripts/naive_align.py
pygor3/scripts/naive_align_id.py
pygor3/scripts/observable.py
pygor3/scripts/pgen_sequences.py
pygor3/scripts/plot_marginals.py
pygor3/scripts/scriptTest.py
pygor3/scripts/scriptTest02.py
pygor3/scripts/short_names_imgt_templates.py
pygor3/scripts/stas_from_bs.py
igorpy-0.0.5.dist-info/LICENSE
igorpy-0.0.5.dist-info/METADATA
igorpy-0.0.5.dist-info/WHEEL
igorpy-0.0.5.dist-info/entry_points.txt
igorpy-0.0.5.dist-info/top_level.txt
igorpy-0.0.5.dist-info/RECORD
